flirt/__init__.py
flirt/acc/__init__.py
flirt/acc/feature_calculation.py
flirt/eda/__init__.py
flirt/eda/feature_calculation.py
flirt/hrv/__init__.py
flirt/hrv/feature_calculation.py
flirt/hrv/features/__init__.py
flirt/hrv/features/data_utils.py
flirt/hrv/features/fd_features.py
flirt/hrv/features/nl_features.py
flirt/hrv/features/td_features.py
flirt/lib/__init__.py
flirt/lib/entropy/__init__.py
flirt/lib/entropy/entropy.py
flirt/lib/entropy/fractal.py
flirt/lib/entropy/utils.py
flirt/reader/__init__.py
flirt/reader/empatica.py
flirt/reader/garmin.py
flirt/reader/holter.py
flirt/simple/__init__.py
flirt/simple/empatica.py
flirt/stats/__init__.py
flirt/stats/common.py
flirt/stats/entropy.py
flirt/stats/feature_calculation.py
flirt/util/__init__.py
flirt/util/io.py
flirt/util/processing.py
flirt/with_/__init__.py
test/__init__.py
test/test_empatica_reader.py
test/test_feature_calculation.py
test/test_filling.py
test/test_stats.py
test/test_with_pkg.py
flirt-0.0.2.dist-info/LICENSE
flirt-0.0.2.dist-info/METADATA
flirt-0.0.2.dist-info/WHEEL
flirt-0.0.2.dist-info/top_level.txt
flirt-0.0.2.dist-info/RECORD
