Metadata-Version: 2.1
Name: flirt
Version: 0.0.2
Summary: Wearable Data Processing Toolkit
Home-page: https://github.com/im-ethz/flirt
Author: ETH Zurich – Chair of Information Management
License: MIT
Platform: UNKNOWN
Classifier: Development Status :: 2 - Pre-Alpha
Classifier: Intended Audience :: Developers
Classifier: Intended Audience :: Science/Research
Classifier: Intended Audience :: Healthcare Industry
Classifier: License :: OSI Approved :: MIT License
Classifier: Programming Language :: Python :: 3.7
Classifier: Programming Language :: Python :: 3.8
Classifier: Programming Language :: Python :: 3.9
Classifier: Natural Language :: English
Requires-Python: >=3.6
Requires-Dist: scipy
Requires-Dist: cvxopt
Requires-Dist: numpy
Requires-Dist: pandas
Requires-Dist: joblib
Requires-Dist: tqdm (>=4.43)
Requires-Dist: ishneholterlib
Requires-Dist: numba
Requires-Dist: astropy
Provides-Extra: all
Requires-Dist: numpydoc ; extra == 'all'
Requires-Dist: m2r2 ; extra == 'all'
Requires-Dist: sphinx-rtd-theme ; extra == 'all'
Requires-Dist: sphinx ; extra == 'all'
Provides-Extra: docs
Requires-Dist: numpydoc ; extra == 'docs'
Requires-Dist: sphinx-rtd-theme ; extra == 'docs'
Requires-Dist: sphinx ; extra == 'docs'
Requires-Dist: m2r2 ; extra == 'docs'
